odoo8_addon_website_sale_collapse_categories-8.0.1.0.0.99.dev8-py2.7-nspkg.pth
odoo8_addon_website_sale_collapse_categories-8.0.1.0.0.99.dev8.dist-info/DESCRIPTION.rst
odoo8_addon_website_sale_collapse_categories-8.0.1.0.0.99.dev8.dist-info/METADATA
odoo8_addon_website_sale_collapse_categories-8.0.1.0.0.99.dev8.dist-info/RECORD
odoo8_addon_website_sale_collapse_categories-8.0.1.0.0.99.dev8.dist-info/WHEEL
odoo8_addon_website_sale_collapse_categories-8.0.1.0.0.99.dev8.dist-info/metadata.json
odoo8_addon_website_sale_collapse_categories-8.0.1.0.0.99.dev8.dist-info/namespace_packages.txt
odoo8_addon_website_sale_collapse_categories-8.0.1.0.0.99.dev8.dist-info/top_level.txt
odoo_addons/website_sale_collapse_categories/README.rst
odoo_addons/website_sale_collapse_categories/__init__.py
odoo_addons/website_sale_collapse_categories/__openerp__.py
odoo_addons/website_sale_collapse_categories/controllers/__init__.py
odoo_addons/website_sale_collapse_categories/controllers/main.py
odoo_addons/website_sale_collapse_categories/i18n/de.po
odoo_addons/website_sale_collapse_categories/i18n/el_GR.po
odoo_addons/website_sale_collapse_categories/i18n/es.po
odoo_addons/website_sale_collapse_categories/i18n/it.po
odoo_addons/website_sale_collapse_categories/i18n/pt_BR.po
odoo_addons/website_sale_collapse_categories/i18n/sl.po
odoo_addons/website_sale_collapse_categories/i18n/website_sale_collapse_categories.pot
odoo_addons/website_sale_collapse_categories/static/description/icon.png
odoo_addons/website_sale_collapse_categories/static/src/css/website_sale.css
odoo_addons/website_sale_collapse_categories/static/src/css/website_sale.css.map
odoo_addons/website_sale_collapse_categories/static/src/css/website_sale.sass
odoo_addons/website_sale_collapse_categories/static/src/js/website_sale.js
odoo_addons/website_sale_collapse_categories/views/website_sale_template.xml
