Metadata-Version: 2.0
Name: odoo8-addon-website-sale-collapse-categories
Version: 8.0.1.0.0.99.dev8
Summary: Collapsible product categories in website shop
Home-page: http://www.serviciosbaeza.com
Author: OpenERP SA, Serv. Tecnol. Avanzados - Pedro M. Baeza, Odoo Community Association (OCA)
Author-email: support@odoo-community.org
License: UNKNOWN
Platform: UNKNOWN
Classifier: Programming Language :: Python
Classifier: Framework :: Odoo
Requires-Python: ~=2.7
Requires-Dist: odoo (<9.0a,>=8.0a)
